r2dt_client-0.1.11.dist-info/METADATA
r2dt_client-0.1.11.dist-info/WHEEL
r2dt_client-0.1.11.dist-info/entry_points.txt
r2dt_client-0.1.11.dist-info/licenses/LICENSE
r2dt_client/__init__.py
r2dt_client/cache/__init__.py
r2dt_client/cache/cache.py
r2dt_client/cache/cache_item.py
r2dt_client/client/__init__.py
r2dt_client/client/client.py
r2dt_client/entities/__init__.py
r2dt_client/entities/exceptions.py
r2dt_client/entities/format.py
r2dt_client/entities/job.py
r2dt_client/entities/job_status.py
r2dt_client/py.typed
r2dt_client/widgets/__init__.py
r2dt_client/widgets/widget.py
r2dt_client-0.1.11.dist-info/RECORD
