Metadata-Version: 2.1
Name: r2dt-client
Version: 0.1.11
Summary: R2DT API Client
Author-Email: Alexey Naiden <r2dt@anaiden.ru>
License: Apache-2.0
Classifier: Development Status :: 4 - Beta
Project-URL: Changelog, https://github.com/anayden/r2dt-client/releases
Project-URL: homepage, https://github.com/anayden/r2dt-client
Project-URL: repository, https://github.com/anayden/r2dt-client
Requires-Python: <4.0,>=3.9
Requires-Dist: diskcache<6.0.0,>=5.6.3
Requires-Dist: httpx<1.0.0,>=0.26.0
Requires-Dist: yarl<2.0.0,>=1.9.4
Requires-Dist: ipython
Requires-Dist: ipywidgets
